Workbook

Sheet Revenue Forecast
B2: Revenue Forecast
B4: Year | C4: Stores | D4: Cust/Day | E4: Spend ($) | F4: Days | G4: Rev/Store | H4: Total Rev | I4: Growth %
B5: 2025 | C5: ='[1]Store Expansion Plan'!$B$2 -> 1 | D5: 200 | E5: ='[1]Optional Scenario Variables'!$B$2 -> 6 | F5: ='[1]Revenue Drivers'!$B$4 -> 360 | G5: =D5*E5*F5 -> 432000 | H5: =G5*C5 -> 432000 | I5: -
B6: 2026 | C6: ='[1]Store Expansion Plan'!$B$3 -> 2 | D6: 210 | E6: ='[1]Optional Scenario Variables'!$C$2 -> 6.5 | F6: ='[1]Revenue Drivers'!$B$4 -> 360 | G6: =D6*E6*F6 -> 491400 | H6: =G6*C6 -> 982800 | I6: =(H6 - H5) / H5 -> 1.275
B7: 2027 | C7: ='[1]Store Expansion Plan'!$B$4 -> 3 | D7: 220 | E7: 7.5 | F7: ='[1]Revenue Drivers'!$B$4 -> 360 | G7: =D7*E7*F7 -> 594000 | H7: =G7*C7 -> 1782000 | I7: =(H7 - H6) / H6 -> 0.81318681

Sheet Expense
B2: Expense
B4: COGS (35% Of Revenue) | E4: Rent Expenses | H4: Salaries and Wages | K4: Other Operating Expense
B5: Year | C5: Value | E5: Year | F5: Value | H5: Year | I5: Value | K5: Year | L5: Value
B6: 2025 | C6: ='Revenue Forecast'!G5*35% -> 151200 | E6: 2025 | F6: ='[1]Cost Assumptions'!$B$3*'Revenue Forecast'!C5*12 -> 36000 | H6: 2025 | I6: ='Revenue Forecast'!C5*'[1]Cost Assumptions'!$B$4*'[1]Cost Assumptions'!$B$6*'[1]Cost Assumptions'!$B$5*360 -> 86400 | K6: 2025 | L6: ='Revenue Forecast'!C5*'[1]Cost Assumptions'!$B$9 -> 15000
B7: 2026 | C7: ='Revenue Forecast'!G6*35% -> 171990 | E7: 2026 | F7: ='[1]Cost Assumptions'!$B$3*'Revenue Forecast'!C6*12 -> 72000 | H7: 2026 | I7: ='Revenue Forecast'!C6*'[1]Cost Assumptions'!$B$4*'[1]Cost Assumptions'!$B$6*'[1]Cost Assumptions'!$B$5*360 -> 172800 | K7: 2026 | L7: ='Revenue Forecast'!C6*'[1]Cost Assumptions'!$B$9 -> 30000
B8: 2027 | C8: ='Revenue Forecast'!G7*35% -> 207900 | E8: 2027 | F8: ='[1]Cost Assumptions'!$B$3*'Revenue Forecast'!C7*12 -> 108000 | H8: 2027 | I8: ='Revenue Forecast'!C7*'[1]Cost Assumptions'!$B$4*'[1]Cost Assumptions'!$B$6*'[1]Cost Assumptions'!$B$5*360 -> 259200 | K8: 2027 | L8: ='Revenue Forecast'!C7*'[1]Cost Assumptions'!$B$9 -> 45000
B11: Expense Category | C11: 2025 | D11: 2026 | E11: 2027 | F11: Notes | G11: Ty
B12: COGS (35%) | C12: =C6 -> 151200 | D12: =C7 -> 171990 | E12: =C8 -> 207900 | F12: 35% of Revenue | G12: Variable
B13: Rent | C13: =F6 -> 36000 | D13: =F7 -> 72000 | E13: =F8 -> 108000 | F13: 3k per store / mo | G13: Fixed
B14: Salaries | C14: =I6 -> 86400 | D14: =I7 -> 172800 | E14: =I8 -> 259200 | F14: 2 staff × 8 h × $15 | G14: Semi-fixed
B15: Marketing | C15: ='[1]Cost Assumptions'!$B$7 -> 10000 | D15: =C15+C15*10% -> 11000 | E15: =D15+D15*10% -> 12100 | F15: +10 % annually | G15: Fixed
B16: Other Expenses | C16: =L6 -> 15000 | D16: =L7 -> 30000 | E16: =L8 -> 45000 | F16: Per store | G16: Fixed
B18: Total Operating Expenses | C18: =SUM(C12:C16) -> 298600 | D18: =SUM(D12:D16) -> 457790 | E18: =SUM(E12:E16) -> 632200

Sheet Income_Statement
B2: Income_Statement
B4: Revenue | E4: COGS | I4: Operating expense
B5: Year | C5: Value | E5: Year | F5: Value | I5: Year | J5: Value
B6: 2025 | C6: ='Revenue Forecast'!H5 -> 432000 | E6: 2025 | F6: =Expense!C6 -> 151200 | I6: 2025 | J6: =Expense!C18 -> 298600
B7: 2026 | C7: ='Revenue Forecast'!H6 -> 982800 | E7: 2026 | F7: =Expense!C7 -> 171990 | I7: 2026 | J7: =Expense!D18 -> 457790
B8: 2027 | C8: ='Revenue Forecast'!H7 -> 1782000 | E8: 2027 | F8: =Expense!C8 -> 207900 | I8: 2027 | J8: =Expense!E18 -> 632200
B11: Line Item | C11: 2025 | D11: 2026 | E11: 2027
B12: Revenue | C12: =C6 -> 432000 | D12: =C7 -> 982800 | E12: =C8 -> 1782000
B13: COGS (35%) | C13: =F6 -> 151200 | D13: =F7 -> 171990 | E13: =F8 -> 207900
B14: Gross Profit | C14: =C12-C13 -> 280800 | D14: =D12-D13 -> 810810 | E14: =E12-E13 -> 1574100
B15: Rent + Salaries + Marketing + Other | C15: =J6 -> 298600 | D15: =J7 -> 457790 | E15: =J8 -> 632200
B16: EBITDA | C16: =C14-C15 -> -17800 | D16: =D14-D15 -> 353020 | E16: =E14-E15 -> 941900
B17: Depreciation (5%) | C17: =C12*5% -> 21600 | D17: =D12*5% -> 49140 | E17: =E12*5% -> 89100
B18: EBIT (Operating Income) | C18: =C16-C17 -> -39400 | D18: =D16-D17 -> 303880 | E18: =E16-E17 -> 852800
B19: Taxes (25%) | C19: =IF(C18>0,C18*25%,0) -> 0 | D19: =IF(D18>0,D18*25%,0) -> 75970 | E19: =IF(E18>0,E18*25%,0) -> 213200
B20: Net Income | C20: =C18-C19 -> -39400 | D20: =D18-D19 -> 227910 | E20: =E18-E19 -> 639600

Sheet DCF
B2: FCF( Free Cash Flow)
B4: Year | C4: EBIT | D4: Taxes | E4: Depreciation | F4: CapEx | G4: Free Cash Flow
B5: 2025 | C5: =Income_Statement!C18 -> -39400 | D5: =Income_Statement!C19 -> 0 | E5: =Income_Statement!C17 -> 21600 | F5: ='[1]Cost Assumptions'!$B$11 -> 20000 | G5: =C5-D5+E5-F5 -> -37800
B6: 2026 | C6: =Income_Statement!D18 -> 303880 | D6: =Income_Statement!D19 -> 75970 | E6: =Income_Statement!D17 -> 49140 | F6: ='[1]Cost Assumptions'!$B$11 -> 20000 | G6: =C6-D6+E6-F6 -> 257050
B7: 2027 | C7: =Income_Statement!E18 -> 852800 | D7: =Income_Statement!E19 -> 213200 | E7: =Income_Statement!E17 -> 89100 | F7: ='[1]Cost Assumptions'!$B$11 -> 20000 | G7: =C7-D7+E7-F7 -> 708700
B9: DCF
B11: Year | C11: Free Cash Flow | D11: Discout Rate | E11: Present Value (PV)
B12: 2025 | C12: =G5 -> -37800 | D12: 0.1 | E12: =C12/(1+D12)^1 -> -34363.636
B13: 2026 | C13: =G6 -> 257050 | D13: 0.1 | E13: =C13/(1+D13)^2 -> 212438.02
B14: 2027 | C14: =G7 -> 708700 | D14: 0.1 | E14: =C14/(1+D14)^3 -> 532456.8

Sheet Cash Flow
B2: Cash Flow
B4: Line Item | C4: 2025 | D4: 2026 | E4: 2027
B5: Net Income | C5: =Income_Statement!C20 -> -39400 | D5: =Income_Statement!D20 -> 227910 | E5: =Income_Statement!E20 -> 639600
B6: + Depreciation | C6: =Income_Statement!C17 -> 21600 | D6: =Income_Statement!D17 -> 49140 | E6: =Income_Statement!E17 -> 89100
B7: Operating Cash Flow | C7: =C5+C6 -> -17800 | D7: =D5+D6 -> 277050 | E7: =E5+E6 -> 728700
B8: CapEx (Investing) | C8: =-DCF!F5 -> -20000 | D8: =-DCF!F6 -> -20000 | E8: =-DCF!F7 -> -20000
B9: Net Cash Change | C9: =C7+C8 -> -37800 | D9: =D7+D8 -> 257050 | E9: =E7+E8 -> 708700
B10: Opening Cash | C10: 0 | D10: =C9 -> -37800 | E10: =D11 -> 219250
B11: Closing Cash | C11: =C10+C9 -> -37800 | D11: =D9+D10 -> 219250 | E11: =E9+E10 -> 927950

Sheet Balance Sheet
B2: Balance Sheet
B4: Line Item | C4: 2025 | D4: 2026 | E4: 2027
B5: Assets
B6: Cash | C6: ='Cash Flow'!C11 -> -37800 | D6: ='Cash Flow'!D11 -> 219250 | E6: ='Cash Flow'!E11 -> 927950
B7: Net Fixed Assets | C7: =DCF!F5-DCF!E5 -> -1600 | D7: =C7+DCF!F6-DCF!E6 -> -30740 | E7: =D7+DCF!F7-DCF!E7 -> -99840
B8: Total Assets | C8: =SUM(C6:C7) -> -39400 | D8: =SUM(D6:D7) -> 188510 | E8: =SUM(E6:E7) -> 828110
B9: Liabilities | C9: 0 | D9: 0 | E9: 0
B10: Equity | C10: ='Cash Flow'!C5 -> -39400 | D10: =C10+'Cash Flow'!D5 -> 188510 | E10: =D10+'Cash Flow'!E5 -> 828110
B11: Assets = Liabilities + Equity | C11: ✅ | D11: ✅ | E11: ✅

Sheet KPI
B2: KPI'S
B4: Metric | C4: 2025 | D4: 2026 | E4: 2027 | F4: Formula Source
B5: Revenue ($) | C5: ='Revenue Forecast'!H5 -> 432000 | D5: ='Revenue Forecast'!H6 -> 982800 | E5: ='Revenue Forecast'!H7 -> 1782000 | F5: From Revenue tab
B6: COGS ($) | C6: =Expense!C12 -> 151200 | D6: =Expense!D12 -> 171990 | E6: =Expense!E12 -> 207900 | F6: From Expense tab
B7: Gross Profit ($) | C7: =C5-C6 -> 280800 | D7: =D5-D6 -> 810810 | E7: =E5-E6 -> 1574100 | F7: Revenue–COGS
B8: Net Income ($) | C8: =Income_Statement!C20 -> -39400 | D8: =Income_Statement!D20 -> 227910 | E8: =Income_Statement!E20 -> 639600 | F8: From Income Statement
B9: Free Cash Flow ($) | C9: =DCF!G5 -> -37800 | D9: =DCF!G6 -> 257050 | E9: =DCF!G7 -> 708700 | F9: From DCF tab
B10: EBITDA Margin (%) | C10: =Income_Statement!C16/KPI!C5 -> -0.041203704 | D10: =Income_Statement!D16/Income_Statement!D12 -> 0.35919821 | E10: =Income_Statement!E16/Income_Statement!E12 -> 0.52856341 | F10: EBITDA / Revenue
B11: Net Profit Margin (%) | C11: =C8/C5 -> -0.091203704 | D11: =D8/D5 -> 0.23189866 | E11: =E8/E5 -> 0.35892256 | F11: Net Income / Revenue
B12: Revenue Growth (%) | C12: – | D12: =(D5-C5)/C5 -> 1.275 | E12: =(E5-D5)/D5 -> 0.81318681 | F12: (ThisYr–LastYr)/LastYr
